{
  "id": "",
  "name": "",
  "font_family": "iconfont",
  "css_prefix_text": "icon-",
  "description": "",
  "glyphs": [
    {
      "icon_id": "26847655",
      "name": "退出",
      "font_class": "tuichu",
      "unicode": "e666",
      "unicode_decimal": 58982
    },
    {
      "icon_id": "27246324",
      "name": "隐藏",
      "font_class": "hide",
      "unicode": "e656",
      "unicode_decimal": 58966
    },
    {
      "icon_id": "27246334",
      "name": "显示",
      "font_class": "show",
      "unicode": "e657",
      "unicode_decimal": 58967
    },
    {
      "icon_id": "27253656",
      "name": "密码",
      "font_class": "mima",
      "unicode": "e611",
      "unicode_decimal": 58897
    },
    {
      "icon_id": "27253678",
      "name": "账号",
      "font_class": "zhanghao",
      "unicode": "e614",
      "unicode_decimal": 58900
    }
  ]
}
